LICENSE
README.md
setup.cfg
setup.py
evduty_free.egg-info/PKG-INFO
evduty_free.egg-info/SOURCES.txt
evduty_free.egg-info/dependency_links.txt
evduty_free.egg-info/requires.txt
evduty_free.egg-info/top_level.txt
evdutyfree/__init__.py
evdutyfree/evdutyfree.py