Metadata-Version: 2.1
Name: evduty-free
Version: 0.0.2a0
Summary: Unofficial module for interacting with EVDuty EV charger api
Home-page: https://github.com/planetefrench/evduty-free
Download-URL: https://github.com/planetefrench/evduty-free/archive/refs/tags/v0.0.1-alpha2.tar.gz
Author: Jean-Marc G
Author-email: none@none.none
License: Apache 2
Classifier: Programming Language :: Python :: 3
Requires-Python: >=3.7
License-File: LICENSE
